{"adverts":[{"address":"Lislary, Ballinfull, Co. Sligo","url":"https://www.daft.ie/for-rent/absolute.rehab/6163027","price":"2200"},{"address":"St Annes Terrace, Sligo, Co. Sligo","url":"https://www.daft.ie/for-rent/absolute.rehab/6164534","price":"1700"},{"address":"Glencarrig 13, Sligo, Co. Sligo","url":"https://www.daft.ie/for-rent/absolute.rehab/6129127","price":"2600"},{"address":"Cartronhugh, Ballintogher, Sligo, Co. Sligo","url":"https://www.daft.ie/for-rent/absolute.rehab/6164506","price":"1550"},{"address":"25 Radharc Na Habhann, Coolaney, Sligo, Beltra, Co. Sligo","url":"https://www.daft.ie/for-rent/absolute.rehab/6164151","price":"1450"},{"address":"Ballinode Sligo Co Sligo F91 H763, Sligo, Co. Sligo","url":"https://www.daft.ie/for-rent/absolute.rehab/6125310","price":"978"},{"address":"bundoran road sligo, Sligo, Co. Sligo","url":"https://www.daft.ie/for-rent/absolute.rehab/6162639","price":"1600"},{"address":"10 beechwood court, oldbundoran Road, Sligo, Co. Sligo","url":"https://www.daft.ie/for-rent/absolute.rehab/6159102","price":"2100"},{"address":"Sea Road, Sligo, Co. Sligo","url":"https://www.daft.ie/for-rent/absolute.rehab/6105256","price":"1800"},{"address":"Saint Angela's Apartments, Calry, Colgagh, Co. Sligo","url":"https://www.daft.ie/for-rent/absolute.rehab/6092819","price":"1800"}],"lastUpdated":"2025-06-09T23:14:12.248Z"}